{
    "intentfolderolds": [],
    "whatsappprofilesettings": [],
    "whatsappwidgets": [],
    "conversationdetailshistories": [],
    "systementities": [],
    "servicetokens": [],
    "dialogflowentities": [],
    "schedulemessageconfigs": [],
    "msteamstokens": [],
    "nlphistories": [],
    "universalauths": [],
    "voximplants": [],
    "assertions": [],
    "flowversions": [
        "difference.0.item.lhs.media.link",
        "difference.48.item.lhs.media.link",
        "difference.50.item.lhs.media.link",
        "difference.52.item.lhs.media.link",
        "difference.181.item.rhs.media.link",
        "difference.183.item.rhs.media.link",
        "difference.185.item.rhs.media.link",
        "difference.0.lhs.thumbnail",
        "difference.0.lhs.blockSteps.8.flowSteps.2.media.link",
        "difference.0.lhs.blockSteps.8.flowSteps.4.media.link",
        "difference.0.lhs.blockSteps.8.flowSteps.6.media.link",
        "difference.0.lhs.blockSteps.0.flowSteps.4.media.link",
        "difference.1.lhs",
        "difference.1.rhs",
        "difference.8.lhs.link",
        "difference.15.lhs.link",
        "difference.22.lhs.link",
        "difference.0.lhs.blockSteps.0.flowSteps.1.media.link",
        "difference.0.lhs.blockSteps.0.flowSteps.2.media.link",
        "difference.0.lhs.blockSteps.0.flowSteps.3.media.link",
        "difference.207.lhs.link",
        "difference.213.lhs",
        "difference.213.rhs",
        "difference.219.lhs",
        "difference.219.rhs",
        "difference.225.lhs",
        "difference.225.rhs",
        "difference.236.rhs.link",
        "difference.0.lhs.blockSteps.0.icon",
        "difference.0.lhs.blockSteps.15.flowSteps.0.media.link",
        "difference.0.lhs.blockSteps.0.flowSteps.5.media.link",
        "difference.36.lhs.link",
        "difference.208.item.rhs.media.link",
        "difference.209.item.rhs.media.link",
        "difference.210.item.rhs.media.link",
        "difference.211.item.rhs.media.link",
        "difference.34.item.lhs.media.link",
        "difference.38.lhs.link",
        "difference.214.item.rhs.media.link",
        "difference.215.item.rhs.media.link",
        "difference.216.item.rhs.media.link",
        "difference.217.item.rhs.media.link",
        "difference.51.item.lhs.media.link",
        "difference.168.item.rhs.media.link",
        "difference.169.item.rhs.media.link",
        "difference.170.item.rhs.media.link",
        "difference.171.item.rhs.media.link",
        "difference.53.item.lhs.media.link",
        "difference.172.item.rhs.media.link",
        "difference.0.lhs.blockSteps.7.flowSteps.1.media.link",
        "difference.88.item.lhs.media.link",
        "difference.253.item.rhs.media.link",
        "difference.254.item.rhs.media.link",
        "difference.255.item.rhs.media.link",
        "difference.256.item.rhs.media.link",
        "difference.63.item.lhs.media.link",
        "difference.178.item.rhs.media.link",
        "difference.179.item.rhs.media.link",
        "difference.180.item.rhs.media.link",
        "difference.87.item.lhs.media.link",
        "difference.173.item.rhs.media.link",
        "difference.174.item.rhs.media.link",
        "difference.175.item.rhs.media.link",
        "difference.176.item.rhs.media.link",
        "difference.234.item.rhs.media.link",
        "difference.235.item.rhs.media.link",
        "difference.236.item.rhs.media.link",
        "difference.237.item.rhs.media.link",
        "difference.0.lhs.blockSteps.4.flowSteps.0.media.link",
        "difference.0.lhs.blockSteps.4.flowSteps.1.media.link",
        "difference.44.rhs.link",
        "difference.21.rhs.link",
        "difference.23.lhs",
        "difference.23.rhs",
        "difference.0.lhs",
        "difference.0.rhs",
        "difference.31.item.rhs.media.link",
        "difference.137.item.rhs.media.link",
        "difference.139.item.rhs.media.link",
        "difference.168.item.lhs.media.link",
        "difference.170.item.lhs.media.link",
        "difference.27.lhs.link",
        "difference.38.rhs.link",
        "difference.7.rhs.link",
        "difference.10.lhs.link",
        "difference.26.rhs.link",
        "difference.28.lhs",
        "difference.28.rhs",
        "difference.17.rhs.link",
        "difference.38.item.lhs.media.link",
        "difference.0.lhs.blockSteps.10.flowSteps.1.media.link",
        "difference.0.lhs.blockSteps.9.flowSteps.1.media.link",
        "difference.0.lhs.blockSteps.7.flowSteps.2.media.link",
        "difference.0.lhs.blockSteps.9.flowSteps.2.media.link",
        "difference.0.lhs.blockSteps.9.flowSteps.3.media.link",
        "difference.0.lhs.blockSteps.7.flowSteps.4.media.link",
        "difference.0.lhs.blockSteps.2.flowSteps.0.media.link",
        "difference.22.item.lhs.media.link",
        "difference.25.lhs",
        "difference.25.rhs",
        "difference.0.lhs.blockSteps.3.flowSteps.0.media.link",
        "difference.0.lhs.blockSteps.5.flowSteps.0.media.link",
        "difference.0.lhs.blockSteps.6.flowSteps.0.media.link",
        "difference.0.lhs.blockSteps.7.flowSteps.0.media.link",
        "difference.0.lhs.blockSteps.8.flowSteps.0.media.link",
        "difference.0.lhs.blockSteps.1.flowSteps.0.list.listItems.0.image",
        "difference.0.lhs.blockSteps.1.flowSteps.0.list.listItems.1.image",
        "difference.0.lhs.blockSteps.1.flowSteps.0.media.link",
        "difference.0.lhs.blockSteps.2.flowSteps.1.media.link",
        "difference.0.lhs.blockSteps.2.flowSteps.2.media.link",
        "difference.0.lhs.blockSteps.2.flowSteps.3.media.link",
        "difference.0.lhs.blockSteps.1.icon",
        "difference.0.lhs.blockSteps.3.icon",
        "difference.0.lhs.blockSteps.4.icon",
        "difference.0.lhs.blockSteps.10.flowSteps.0.media.link",
        "difference.0.lhs.blockSteps.10.flowSteps.2.media.link",
        "difference.5.item.lhs.icon",
        "difference.15.item.lhs.flowSteps.0.card.image",
        "difference.15.item.lhs.flowSteps.0.card.url",
        "difference.16.item.lhs.flowSteps.0.carousels.0.image",
        "difference.101.rhs"
    ],
    "slacksettings": [],
    "departments": [],
    "flowblocksteps": [
        "icon"
    ],
    "bottriggerpoints": [],
    "apitools": [],
    "unpublished-flows": [
        "thumbnail"
    ],
    "widgetconsentscreens": [],
    "users": [],
    "snapshotsteps": [],
    "conversations": [
        "conversationData"
    ],
    "accesses": [],
    "intentfolders": [],
    "dialogflowauths": [],
    "growthtools": [],
    "unpublished-flowblocksteps": [
        "icon"
    ],
    "campaigns": [],
    "dialogflowintents": [],
    "instagramsettings": [],
    "rules": [],
    "tags": [],
    "services": [],
    "templatemessages": [],
    "bots": [],
    "broadcastexecutors": [],
    "flowfolders": [],
    "forms": [],
    "dialogflowsytementities": [],
    "newIntent": [],
    "fallbacktrainings": [],
    "flowsteps": [
        "media.link",
        "list.listItems.0.image",
        "list.listItems.1.image",
        "card.url"
    ],
    "bdks": [],
    "dialogflowtokens": [],
    "nlps": [],
    "ibmdiscoverydocuments": [],
    "taganalytics": [],
    "audiocodessettings": [],
    "ruleexecutors": [],
    "navigators": [],
    "operations": [],
    "botusers": [
        "systemCustomFields.profile_pic"
    ],
    "handoff-designs": [],
    "transcripts": [],
    "handoffs": [],
    "audits": [
        "documentAfterAccess.thumbnail",
        "documentAfterAccess.icon",
        "documentAfterAccess.chatBotDesign.botImage",
        "documentAfterAccess.card.image",
        "documentAfterAccess.card.url",
        "documentAfterAccess.carousels.0.image",
        "documentAfterAccess.logo"
    ],
    "intentmappings": [],
    "nlptraininghistories": [],
    "handoff-messages": [],
    "intents": [],
    "sankygraphs": [],
    "fallbacks": [],
    "previewlinks": [],
    "confusionmatrixes": [],
    "whatsapptemplatemessages": [],
    "icons": [],
    "knowledgebases": [],
    "notes": [],
    "unpublished-flowsteps": [
        "media.link",
        "card.url"
    ],
    "userfis": [],
    "flowhistories": [],
    "profiles": [],
    "conversationhistories": [],
    "dialogflowtrainings": [],
    "fis": [],
    "organizations": [],
    "flows": [],
    "keywords": [],
    "multinlps": [],
    "saasagendajobs": [],
    "mediauploads": [],
    "agendaJobs": [],
    "entities": [],
    "messages": [
        "attachment.contentUrl"
    ],
    "snapshots": []
}